LICENSE
README.md
setup.py
srsparser/__init__.py
srsparser/configs.py
srsparser/language_processor.py
srsparser/parser.py
srsparser/sections_tree.py
srsparser/utils.py
srsparser.egg-info/PKG-INFO
srsparser.egg-info/SOURCES.txt
srsparser.egg-info/dependency_links.txt
srsparser.egg-info/requires.txt
srsparser.egg-info/top_level.txt