Metadata-Version: 2.1
Name: srsparser
Version: 1.4.8
Summary: A library that translates semi-structured documents into a structured form and contains natural language processing algorithms.
Home-page: UNKNOWN
Author: Kurmyza Pavel
Author-email: tmrrwnxtsn@gmail.com
License: UNKNOWN
Project-URL: Code, https://github.com/Text-Analysis/srsparser/
Project-URL: Issue Tracker, https://github.com/Text-Analysis/srsparser/issues
Project-URL: Download, https://pypi.org/project/srsparser/
Keywords: parser,text,documents,docx,nlp
Platform: UNKNOWN
Classifier: Programming Language :: Python :: 3.7
Classifier: License :: OSI Approved :: GNU General Public License v3 (GPLv3)
Classifier: Topic :: Text Processing :: Linguistic
Requires-Python: >=3.7
License-File: LICENSE
